livestock_win/__init__.py
livestock_win/misc.py
livestock_win/ssh.py
livestock_win/win_cmf.py
livestock_win-0.0.1.dev5.dist-info/DESCRIPTION.rst
livestock_win-0.0.1.dev5.dist-info/METADATA
livestock_win-0.0.1.dev5.dist-info/RECORD
livestock_win-0.0.1.dev5.dist-info/WHEEL
livestock_win-0.0.1.dev5.dist-info/entry_points.txt
livestock_win-0.0.1.dev5.dist-info/metadata.json
livestock_win-0.0.1.dev5.dist-info/top_level.txt
